<?xml version="1.0" encoding="iso-8859-1"?>
<parametres_synoptiqueAutoclaves>
  <!-- clé de licence -->
  <licenceKey>c43a6286271722779bd4b1631abde7cd</licenceKey>
  <pwd>76203e16c2ef8d4c9c43c265b3724e</pwd>
  <!-- Initialisation des embases -->
  <NbEmbases>120</NbEmbases>
  <NbEmbasesDansAutoclave>10</NbEmbasesDansAutoclave>
  <!-- Initialisation des autoclaves -->
  <NbAutoclavesGlycole>4</NbAutoclavesGlycole>
  <NbAutoclavesReseau>8</NbAutoclavesReseau>
  <DureeChargementAutoclaves>3</DureeChargementAutoclaves>
  <DureeDechargementAutoclaves>5</DureeDechargementAutoclaves>
  <DureeDechargementEmbases>10</DureeDechargementEmbases>
  <!-- Initialisation des heures de départ -->
  <HeureDepartLigne1>8</HeureDepartLigne1>
  <MinuteDepartLigne1>0</MinuteDepartLigne1>
  <HeureDepartLigne2>8</HeureDepartLigne2>
  <MinuteDepartLigne2>5</MinuteDepartLigne2>
  <HeureDepartLigne3>8</HeureDepartLigne3>
  <MinuteDepartLigne3>10</MinuteDepartLigne3>
  <HeureDepartLigne4>8</HeureDepartLigne4>
  <MinuteDepartLigne4>15</MinuteDepartLigne4>
  <HeureDepartLigne5>8</HeureDepartLigne5>
  <MinuteDepartLigne5>20</MinuteDepartLigne5>
</parametres_synoptiqueAutoclaves>